Workbook

Sheet Master
A1: Year | B1: SH | C1: Project Name | D1: Department | E1: Risk Area | F1: Descriptions | G1: Code | H1: Bobot | I1: Kadar | J1: Nilai
A2: 2022 | B2: SH1 | C2: Century21 | D2: Departemen Franchise Development Department (FDD) | E2: Kelengkapan dokumen sebagai persyaratan administratif bagi MB Baru, MB Renewal, dan MB yang tutup. (Kelengkapan dokumen yang harus dipenuhi oleh setiap MB baik yang baru maupun yang masih aktif adalah Akte Pendirian PT/CV (badan Usaha), KTP, SIUP, TDP, NPWP, dan Pengesahan Menkeh; sedangkan untuk MB yang ingin mengakhiri kerja sama harus mengirimkan surat pengakhiran kerja sama ke pihak C21) | F2: Berdasarkan pemeriksaan atas perjanjian Waralaba Century21 Primary Network, ditemukan PKS belum ditandatangani oleh pihak Franchisor dan Franchisee berselang 397 hari sejak PKS dibuat s/d cut off audit 24 Mar’22; Klausul pada PKS menyebutkan ada Dana Periklanan Nasional namun dalam penerapannya tidak ada. (Temuan ulangan) | G2: F | H2: 2 | I2: 2.5 | J2: 5
A3: 2022 | B3: SH1 | C3: Century21 | D3: Departemen Franchise Development Department (FDD) | E3: Kelengkapan dokumen sebagai persyaratan administratif bagi MB Baru, MB Renewal, dan MB yang tutup. (Kelengkapan dokumen yang harus dipenuhi oleh setiap MB baik yang baru maupun yang masih aktif adalah Akte Pendirian PT/CV (badan Usaha), KTP, SIUP, TDP, NPWP, dan Pengesahan Menkeh; sedangkan untuk MB yang ingin mengakhiri kerja sama harus mengirimkan surat pengakhiran kerja sama ke pihak C21) | F3: Berdasarkan pemeriksaan atas perjanjian kerjasama pemasaran antara PT Kota Podomoro Tenjo Sejahtera (Developer) dengan Century21 Indonesia (Lead Agent), ditemukan Tidak ada Perjanjian atau Internal Memo yang menjelaskan fee konsorsium sebesar 0.5% harus dibagi rata antara PT. Fitria Kusuma Persada (Century21), PT Properti Maxima International (Promex) dan PT Era Graharealty Tbk (ERA) | G3: F | H3: 2 | I3: 2.5 | J3: 5
A4: 2022 | B4: SH1 | C4: Century21 | D4: Departemen Franchise Development Department (FDD) | E4: Renewal MB (Setiap MB yang renewal harus sesuai dengan price list yang ada, bila tidak sesuai dengan price list yang ada, maka harus mendapatkan persetujuan dari Direktur) | G4: NF | H4: 0 | I4: 0 | J4: 0
A5: 2022 | B5: SH1 | C5: Century21 | D5: Departemen Franchise Development Department (FDD) | E5: Nilai Franchise fee, Royalty, Annually fee, NAF (Setiap nilai maupun ketentuan dari Franchise fee, Royalty, Annually fee, NAF harus sesuai dengan price list yang ada, bila tidak sesuai dengan price list yang ada, maka harus mendapatkan persetujuan dari Direktur) | G5: NF | H5: 0 | I5: 0 | J5: 0
A6: 2022 | B6: SH1 | C6: Century21 | D6: Departemen Franchise Development Department (FDD) | E6: Lokasi penyebaran MB (Penyebaran lokasi dapat di bandingkan dangan jumlah penyebaran franchise broker pesaing (ERA, Ray white dll) | G6: NF | H6: 0 | I6: 0 | J6: 0
A7: 2022 | B7: SH1 | C7: Century21 | D7: Departemen Franchise Support Development (FSD) | E7: Eksklusif Listing, Open Listing dan PJP | G7: NF | H7: 0 | I7: 0 | J7: 0
A8: 2022 | B8: SH1 | C8: Century21 | D8: Departemen Franchise Support Development (FSD) | E8: Kurang lengkapnya informasi yang disajikan pada laporan transaksi | G8: NF | H8: 0 | I8: 0 | J8: 0
A9: 2022 | B9: SH1 | C9: Century21 | D9: Departemen Franchise Support Development (FSD) | E9: Komisi yang diterima oleh C21 (komisi diberikan atas semua unit yang terjual dan sesuai dengan ketentuan yang berlaku) | G9: NF | H9: 0 | I9: 0 | J9: 0
A10: 2022 | B10: SH1 | C10: Century21 | D10: Departemen Franchise Support Development (FSD) | E10: Transaksi referral dan co-broking (Setiap transaksi referral dan co-broking harus mempunyai surat pernyataan dari MB yang mempunyai transaksi tsb) | G10: NF | H10: 0 | I10: 0 | J10: 0
A11: 2022 | B11: SH1 | C11: Century21 | D11: Departemen Franchise Support Development (FSD) | E11: Pengelolaan barang souvenir (Pengelolaan barang souvenir harus mempunyai kartu stock persediaan, dan mutasi keluar masuk barang harus ada bukti terima/keluar barang yang di setujui oleh pihak yang berwenang) | G11: NF | H11: 0 | I11: 0 | J11: 0
A12: 2022 | B12: SH1 | C12: Century21 | D12: Departemen Franchise Support Development (FSD) | E12: Training (Memastikan setiap kebijakan training mendapat persetujuan dari pihak berwenang, administrasi pendaftaran training sudah lengkap, penagihan biaya training dilakukan dengan baik) | G12: NF | H12: 0 | I12: 0 | J12: 0
A13: 2022 | B13: SH1 | C13: Century21 | D13: Departemen Franchise Support Development (FSD) | E13: Pemberian Award kepada MB dan MA (award yang didapat sesuai dengan pencapaian oleh MB/MA) | G13: NF | H13: 0 | I13: 0 | J13: 0
A14: 2022 | B14: SH1 | C14: Century21 | D14: Departemen Franchise Support Development (FSD) | E14: Kegiatan pembelian (Pembelian barang-barang dilakukan oleh purchasing; setiap pembelian dilakukan perbandingan minimal 3 supplier; setiap permintaan barang harus didahului oleh PR dan disetujui oleh pihak yang berwenang; setiap pembelian harus mempunyai PO dan disetujui oleh pihak yang berwenang) | G14: NF | H14: 0 | I14: 0 | J14: 0
A15: 2022 | B15: SH1 | C15: Century21 | D15: Departemen ICD | E15: Software yang ada (setiap MB diberikan paket software dan diberikan pelatihan cara menggunakannya) | G15: NF | H15: 0 | I15: 0 | J15: 0
... A17: 2022 | B17: SH1 | C17: Century21 | D17: Departemen ICD | E17: Monitoring Maintenace Website Century | G17: NF | H17: 0 | I17: 0 | J17: 0
A18: 2022 | B18: SH1 | C18: Century21 | D18: Departemen Finance And Accounting Departement (FAD) | E18: Cash dan Bank Management (dilakukan opname berkala dan didukung Berita Acara, setiap mutasi yang terjadi harus dicatat dan diupdate, kas bon dicatat terpisah dari buku kas harian dan harus dimonitor batas pertanggung jawabannya) | F18: Berdasarkan cash opname pada tanggal 17 Mar’22, ditemukan Reimbursement kas kecil ditransfer ke rekening pribadi PIC (Admin Marketing); Belum dilakukan cash opname rutin secara berkala yang dilengkapi dengan Berita Acara Opname yang ditandatangani oleh Finance & Accounting Manager | G18: F | H18: 2 | I18: 3 | J18: 6
A19: 2022 | B19: SH1 | C19: Century21 | D19: Departemen Finance And Accounting Departement (FAD) | E19: Cash dan Bank Management (dilakukan opname berkala dan didukung Berita Acara, setiap mutasi yang terjadi harus dicatat dan diupdate, kas bon dicatat terpisah dari buku kas harian dan harus dimonitor batas pertanggung jawabannya) | F19: Berdasarkan sample check atas 20 transaksi pembayaran menggunakan Cheque/Giro, ditemukan seluruh pembayaran untuk kasbon ditransfer ke rekening pribadi karyawan | G19: F | H19: 2 | I19: 3 | J19: 6
A20: 2022 | B20: SH1 | C20: Century21 | D20: Departemen Finance And Accounting Departement (FAD) | E20: Piutang dan Collection (aging schedule dimonitor setiap bulannya dan dikirimkan surat peringatan atas konsumen yang melakukan tunggakan) | F20: Berdasarkan sample check pembayaran tagihan atas 4 MB, ditemukan 4 MB yang pencatatan umur tunggakan di monitoring aging tidak diklasifikasikan berdasarkan urutan umur tagihan; 2 MB yang berdasarkan pemeriksaan Audit membayar bukan dari periode terlama (Temuan ulangan) | G20: F | H20: 2 | I20: 3.5 | J20: 7
A21: 2022 | B21: SH1 | C21: Century21 | D21: Departemen Finance And Accounting Departement (FAD) | E21: Piutang dan Collection (aging schedule dimonitor setiap bulannya dan dikirimkan surat peringatan atas konsumen yang melakukan tunggakan) | F21: Berdasarkan sample check pembayaran annual fee atas 56 MB, ditemukan tunggakan annual fee atas 4 MB yang belum dicatat dalam aging, di mana tunggakan tersebut hanya tercatat dalam rekap manual dengan total Rp 20,000,000 dan telah berumur berkisar 184 hari s/d 427 hari sejak tanggal jatuh tempo s/d pullout audit 18 Mar’22 | G21: F | H21: 2 | I21: 3.5 | J21: 7
A22: 2022 | B22: SH1 | C22: Century21 | D22: Departemen Finance And Accounting Departement (FAD) | E22: Internal Control Lintas Departemen (Fin Acc harus menjalankan fungsi control, bukan hanya mencatat saja) | F22: Berdasarkan full check atas 16 penerimaan sponsorship ditemukan tidak konsisten-nya pencatatan atas penerimaan sponsorship di mana di catat pada 2 Akun yaitu Akun Pendapatan Lain-lain (32.10.190) dan Akun Commision BCA (32.40.120) | G22: F | H22: 2 | I22: 4.5 | J22: 9
A23: 2022 | B23: SH1 | C23: Century21 | D23: Departemen Finance And Accounting Departement (FAD) | E23: Internal Control Lintas Departemen (Fin Acc harus menjalankan fungsi control, bukan hanya mencatat saja) | F23: Berdasarkan pemeriksaan atas investasi berupa saham yang tercantum di Neraca ditemukan kesalahan pencatatan atas penerimaan deviden tahun 2021, di mana saat penerimaan deviden tidak dicatat sebagai pendapatan deviden (kredit), melainkan dicatat pada akun RDN SAG001 (11.20.400) sehingga menyebabkan saldo pendapatan deviden dan akun RDN SAG001 understated sebesar Rp 15,520,590 (Temuan ulangan) | G23: F | H23: 2 | I23: 4.5 | J23: 9
A24: 2022 | B24: SH1 | C24: Century21 | D24: Departemen Finance And Accounting Departement (FAD) | E24: Internal Control Lintas Departemen (Fin Acc harus menjalankan fungsi control, bukan hanya mencatat saja) | F24: Berdasarkan analisa account Piutang Lainnya (No.Akun: 11.30.990) per 31 Des’21, ditemukan saldo akun Piutang Lainnya bersaldo minus sebesar Rp 39,332,074 (Sagotra Usaha) | G24: F | H24: 2 | I24: 4.5 | J24: 9
A25: 2022 | B25: SH1 | C25: Century21 | D25: Departemen Finance And Accounting Departement (FAD) | E25: Internal Control Lintas Departemen (Fin Acc harus menjalankan fungsi control, bukan hanya mencatat saja) | F25: Saldo Piutang lainnya per Des’19 sebesar Rp 1,691,673,996 merupakan saldo bawaan kumulatif s/d Dec’19 yang tidak terinci secara detail sehingga saldo Des’20 menjadi sebesar Rp. 134,588,124 (Fitria Kusuma Persada) | G25: F | H25: 2 | I25: 4.5 | J25: 9
A26: 2022 | B26: SH1 | C26: Century21 | D26: Departemen Finance And Accounting Departement (FAD) | E26: Internal Control Lintas Departemen (Fin Acc harus menjalankan fungsi control, bukan hanya mencatat saja) | F26: Berdasarkan pemeriksaan atas pengakuan sewa ruko sebesar Rp 110,000,000 (termasuk PPN) ditemukan kesalahan pencatatan atas penerimaan sewa ruko, di mana penerimaan dicatat pada akun Pendapatan Lain-lain padahal seharusnya dicatat pada akun Sewa Diterima Dimuka (Temuan ulangan) | G26: F | H26: 2 | I26: 4.5 | J26: 9
A27: 2022 | B27: SH1 | C27: Century21 | D27: Departemen Finance And Accounting Departement (FAD) | E27: Internal Control Lintas Departemen (Fin Acc harus menjalankan fungsi control, bukan hanya mencatat saja) | F27: Penerimaan NAF (No.Akun: 11.70.100) bersaldo kredit dan Pengeluaran NAF (No. Akun: 11.70.200) bersaldo debit dicatat pada dua akun asset yang berbeda dan tidak dilakukan offset | G27: F | H27: 2 | I27: 4.5 | J27: 9
A28: 2022 | B28: SH1 | C28: Century21 | D28: Departemen Finance And Accounting Departement (FAD) | E28: Pengelolaan dan Pengamanan Asset (Setiap Aset harus di data (nilai, tgl bln thn perolehan, jenis barang, nama barang, kode barang)) | F28: Berdasarkan full check perhitungan depresiasi atas 91 item (121 pcs) inventaris asset per 31 Des’21 ditemukan selisih perhitungan biaya penyusutan dan akumulasi penyusutan atas 21 item inventaris asset (22 pcs) antara Asset List dengan perhitungan audit di mana terdapat overstated nilai Biaya Penyusutan Inventaris Kantor sebesar Rp 1,085,522 dan Understated Akumulasi Penyusutan Inventaris Kantor yang mengakibatkan overstated nilai buku sebesar Rp 2,542,134; Selisih perhitungan Biaya Penyusutan dan Akumulasi Penyusutan Inventaris antara Trial Balance per 31 Dec’21 dengan perhitungan Audit masing-masing sebesar Rp 9,005,802 dan Rp 1,063,315 (Temuan ulangan) | G28: F | H28: 2 | I28: 4.5 | J28: 9
A29: 2022 | B29: SH1 | C29: Century21 | D29: Departemen Finance And Accounting Departement (FAD) | E29: Pengelolaan dan Pengamanan Asset (Setiap Aset harus di data (nilai, tgl bln thn perolehan, jenis barang, nama barang, kode barang)) | F29: Berdasarkan pemeriksaan atas akun MLS Software (No.Akun: 16.50.100) per 31 Dec’21 sebesar Rp 2,001,000,000, ditemukan Asset Software tersebut belum diamortisasi dan understated Rp 120,000,000 karena kesalahan pencatatan atas penerimaan sewa aplikasi di mana seharusnya diakui sebagai pendapatan namun dicatat sebagai pengurang asset. (PT Fitria Kusumapersada) | G29: F | H29: 2 | I29: 4.5 | J29: 9
... A32: 2022 | B32: SH1 | C32: Century21 | D32: Departemen Finance And Accounting Departement (FAD) | E32: Pembelanjaan Dept Purchasing (dilakukan sesuai dengan prosedur pengadaan barang yaitu dengan SPK/PO, perbandingan harga minimal 3 supplier, disetujui sesuai koridor; pengelolaan atas barang yang ada dilakukan dengan baik). | F32: Berdasarkan pemeriksaan pemeriksan pembayaran sewa mesin fotocopy atas 4 transaksi pembayaran sewa mesin fotocopy, ditemukan Dokumen Perjanjian Sewa tidak diarsip dengan baik dan tidak ada addendum perpanjangan atas sewa tersebut; Rata-rata pemakaian untuk 4 bulan hanya sebesar 1,462 lembar (37%) dari minimum pemakaian kertas; Tidak dipotongkan PPN dan PPh 23 atas sewa Mesin Fotocopy | G32: F | H32: 2 | I32: 2 | J32: 4
A33: 2022 | B33: SH1 | C33: Century21 | D33: HRD | E33: Monitoring Lembur (setiap lembur harus didukung dengan SPL yang dibuat sebelum pekerjaan lembur dijalankan/maksimal satu hari setelah lembur, disetujui atasan yang berwenang, jam kerja yang diperhitungkan sebagai lembur adalah yang lebih kecil antara absensi vs jam di SPL, jika absensi lebih besar dan memang dibutuhkan penyesuaian jam lembur maka SPL harus direvisi ulang) | G33: NF | H33: 0 | I33: 0 | J33: 0
A34: 2022 | B34: SH1 | C34: Century21 | D34: HRD | E34: Absensi (setiap karyawan harus melakukan absensi setiap harinya, apabila tidak absen harus didukung dengan form ijin/cuti/tugas kantor yang disetujui atasan ybs) | F34: Berdasarkan full check atas 21 karyawan selama bulan Okt’21, ditemukan 21 karyawan (160 hari kerja), pada system tercatat tidak absen masuk dan absen pulang namun tidak ada keterangan; Tidak terdapat pembagian hari kerja WFH dan WFO secara tertulis; 8 karyawan (27 hari kerja), di mana karyawan tersebut pada system hanya tercatat absen masuk; Selama ini tidak pernah dilakukan monitoring absensi oleh PIC Absensi; Tidak dapat dilakukan pengecekan pemakaian dan sisa cuti karyawan, karena PIC Absensi tidak memiliki akses untuk menarik data pemakaian dan sisa cuti karyawan pada HCMS | G34: F | H34: 2 | I34: 4 | J34: 8
A35: 2022 | B35: SH1 | C35: Century21 | D35: HRD | E35: Absensi (setiap karyawan harus melakukan absensi setiap harinya, apabila tidak absen harus didukung dengan form ijin/cuti/tugas kantor yang disetujui atasan ybs) | F35: Berdasarkan sample check atas 6 bulan pembayaran Tunjangan Transport di mana untuk pembayaran bulan Okt’21 dilakukan sample ke data tarikan absensi, ditemukan seluruh pembayaran tunjangan transport tidak dilampirkan dengan data tarikan absensi; Terdapat perbedaan jumlah hari kerja atas 4 karyawan yang mendapatkan tunjangan transport antara yang tercatat di data rekapan untuk pembayaran Tunjangan Transport dengan data tarikan absensi di bulan Okt’21 | G35: F | H35: 2 | I35: 4 | J35: 8
A36: 2022 | B36: SH1 | C36: Century21 | D36: HRD | E36: Biaya Pengobatan (untuk biaya pengobatan yang menjadi tanggungan manajemen harus dikontrol dengan baik agar reimburse sesuai ketentuan dan tidak ada karyawan yang over plafond) | F36: Berdasarkan full check atas 1 karyawan yang mengajukan claim persalinan, ditemukan klaim penggantian biaya persalinan yang lebih besar dari ketentuan di mana seharusnya hanya sebesar 85% dari nilai kuitansi namun terbayar 100% dari nilai kuitansi | G36: F | H36: 2 | I36: 3 | J36: 6
A37: 2022 | B37: SH1 | C37: Century21 | D37: HRD | E37: Biaya Pengobatan (untuk biaya pengobatan yang menjadi tanggungan manajemen harus dikontrol dengan baik agar reimburse sesuai ketentuan dan tidak ada karyawan yang over plafond) | F37: Berdasarkan full check atas 20 pembayaran Asuransi Karyawan (Mandiri Inhealth), ditemukan 2 karyawan yang menerima benefit asuransi tidak sesuai dengan golongan karyawan yang bersangkutan | G37: F | H37: 2 | I37: 3 | J37: 6
A38: 2022 | B38: SH1 | C38: Century21 | D38: HRD | E38: Biaya Pengobatan (untuk biaya pengobatan yang menjadi tanggungan manajemen harus dikontrol dengan baik agar reimburse sesuai ketentuan dan tidak ada karyawan yang over plafond) | F38: Berdasarkan full check atas 20 pembayaran BPJS Kesehatan selama tahun 2021 ditemukan 9 karyawan yang BPJS kesehatannya tidak dibayarkan berselang 4 bulan s/d 59 bulan sejak deadline awal BPJS seharusnya dibayarkan dari tanggal masuk sampai dengan tanggal cut off audit 31 Des’2021; 3 karyawan yang BPJS kesehatannya mengikuti pembayaran BPJS suami, namun tidak dilengkapi dengan surat keterangan yang menjelaskan ybs mengikuti pembayaran BPJS suami | G38: F | H38: 2 | I38: 3 | J38: 6
A39: 2022 | B39: SH1 | C39: Century21 | D39: HRD | E39: Clearence Exit (HRD harus mengontrol serah terima baik pekerjaan maupun inventaris dari setiap karyawan yang mau mengudurkan diri). | G39: NF | H39: 0 | I39: 0 | J39: 0
A40: 2022 | B40: SH1 | C40: Century21 | D40: HRD | E40: Training ((Fasilitas training seharusnya diberikan kepada karyawan yang memenuhi syarat dan biaya yang dikeluarkan tidak melebihi budget; Terdapat sertifikat atas setiap training yang diikuti sebagai bukti keikutsertaan dalam training). | G40: NF | H40: 0 | I40: 0 | J40: 0
A41: 2022 | B41: SH1 | C41: Century21 | D41: HRD | E41: Karyawan kontrak dan pengelolaannya (kontrak karyawan harus sesuai dengan ketentuan yang berlaku yaitu maksimal 2x kontrak dengan masa kontrak 3 tahun yang dimana kontrak kedua maksimum 1 tahun; kontrak yang ada masih valid/belum expired; mutasi/promosi harus didukung dengan IM yang disetujui yang berwenang) | F41: Berdasarkan full check atas 10 karyawan Departemen Marketing yang bekerja selama periode Jan’21 s/d Des’21, ditemukan 7 kontrak karyawan yang telah expired namun belum dibuatkan perpanjangan kontrak, di mana 2 kontrak telah berakhir berkisar 205 hari dan 219 hari dan 5 kontrak belum diperpanjang berkisar 13 hari s/d 193 hari dari tanggal berakhir kontrak s/d tanggal karyawan tersebut resigned; Hasil evaluasi sales yang hanya secara lisan dan tidak dibuatkan secara tertulis, padahal sales tidak mencapai target penjualan dan seharusnya sudah berakhir di bulan ketiga | G41: F | H41: 2 | I41: 2 | J41: 4
A42: 2024 | B42: SH1 | C42: Ciputra Artpreneur | D42: Departemen Marketing | E42: Transaksi Penjualan patung/ souvenir/ penyewaan ruangan/ penyewaan space, dll: (harga jual yang dikenakan harus sesuai dengan PL, setiap keringanan yang diberikan (diskon harga maupun kelonggaran cara bayar) harus didukung persetujuan yang berwenang sesuai koridor). | G42: NF | H42: 0 | I42: 0 | J42: 0
A43: 2024 | B43: SH1 | C43: Ciputra Artpreneur | D43: Departemen Marketing | E43: Penerbitan Surat Pemesanan/ Surat Perjanjian atas pemesanan patung, sewa ruang, dan penerimaan lainnya: (pemesanan patung/ souvenir/ sewa ruang/ event sebaiknya didukung dengan Surat Pemesanan yang bernomor urut tercetak yang mencantumkan jenis patung, dan opsi-opsi lainnya seperti akan dilapis warna apa, ada plat nama atua tidak, dll serta ditandatangani kedua belah pihak). | G43: NF | H43: 0 | I43: 0 | J43: 0
A44: 2024 | B44: SH1 | C44: Ciputra Artpreneur | D44: Departemen Marketing | E44: Subkontraktor (pemberian pekerjaan ke pihak ketiga): (pemberian pekerjaan ke pihak ketiga agar didukung dengan proses perbandingan harga, apabila hanya satu subkon agar didukung dengan IM tertulis yang disetujui Pihak Berwenang) | G44: NF | H44: 0 | I44: 0 | J44: 0
A45: 2024 | B45: SH1 | C45: Ciputra Artpreneur | D45: Departemen Marketing | E45: Kegiatan Promosi (memastikan bahwa pembelanjaan promosi sesuai dengan budget yang telah ditetapkan; dilakukan sesuai dengan prosedur pengadaan barang yaitu dengan SPK/PO, perbandingan harga minimal 3 supplier, disetujui sesuai koridor; pengelolaan atas barang yang ada dilakukan dengan baik). | F45: Berdasarkan sample check atas 45 PO ditemukan 6 PO atas pekerjaan jasa yang tidak diterbitkan melalui SPK; 1 PO Repeat Order ke supplier yang sama padahal item pembelian dan harga berbeda; 1 transaksi pembelian yang tidak dilengkapi dengan PO; Approval atas 3 PO yang tidak sesuai dengan koridor approval | G45: F | H45: 2 | I45: 3 | J45: 6
A46: 2024 | B46: SH1 | C46: Ciputra Artpreneur | D46: Departemen Marketing | E46: Kegiatan Promosi (memastikan bahwa pembelanjaan promosi sesuai dengan budget yang telah ditetapkan; dilakukan sesuai dengan prosedur pengadaan barang yaitu dengan SPK/PO, perbandingan harga minimal 3 supplier, disetujui sesuai koridor; pengelolaan atas barang yang ada dilakukan dengan baik). | F46: Berdasarkan full opname atas 2 barang souvenir ditemukan tidak pernah dilakukan stock opname secara rutin | G46: F | H46: 2 | I46: 3 | J46: 6
A47: 2024 | B47: SH1 | C47: Ciputra Artpreneur | D47: Departemen Marketing | E47: Kegiatan Promosi (memastikan bahwa pembelanjaan promosi sesuai dengan budget yang telah ditetapkan; dilakukan sesuai dengan prosedur pengadaan barang yaitu dengan SPK/PO, perbandingan harga minimal 3 supplier, disetujui sesuai koridor; pengelolaan atas barang yang ada dilakukan dengan baik). | F47: Berdasarkan sample check atas 14 SPK ditemukan 1 SPK pekerjaan tambah yang approvalnya tidak kumulatif dengan SPK awal sehingga approval menjadi tidak sesuai dengan koridor yang berlaku; 1 SPK Tunjuk Langsung yang penerbitan Berita Acara Penunjukkannya diterbitkan 72 hari setelah tanggal SPK terbit; 2 SPK atas pembelian barang dan tidak ada jasanya yang diterbitkan melalui PO. | G47: F | H47: 2 | I47: 3 | J47: 6
A48: 2024 | B48: SH1 | C48: Ciputra Artpreneur | D48: Departemen House Keeping | E48: Kerja sama dengan pihak ketiga (didukung dengan MOU, kinerja outsourcing harus dipastikan sesuai dengan harapan manajemen dan tidak merugikan pihak manajemen) | F48: Berdasarkan permintaan data outsourcing Security ditemukan data belum diberikan ke team Internal Audit berselang 50 hari sejak tanggal permintaan data dikirimkan s/d tanggal 5 Apr’24 | G48: F | H48: 1 | I48: 1 | J48: 1
A49: 2024 | B49: SH1 | C49: Ciputra Artpreneur | D49: Departemen House Keeping | E49: Monitoring Pest Control | G49: NF | H49: 0 | I49: 0 | J49: 0
A50: 2024 | B50: SH1 | C50: Ciputra Artpreneur | D50: Departemen Engineering | E50: Lain-lain (pengelolaan dan pengecekan atas keadaan atau kondisi artpreneur secara keseluruhan, seperti kondisi bangunan, peralatan alaram kebakaran, dll) | F50: Berdasarkan hasil observasi kebersihan area Ciputra Artpreneur pada tanggal 23 Feb’24 dan 27 Feb’24 ditemukan kolam lobby Lt.11 Ciputra Artpreneur dalam keadaan kotor, dipenuhi lumut dan terdapat bangkai ikan di pinggir kolam | G50: F | H50: 2 | I50: 5 | J50: 10
A51: 2024 | B51: SH1 | C51: Ciputra Artpreneur | D51: Departemen Engineering | E51: Lain-lain (pengelolaan dan pengecekan atas keadaan atau kondisi artpreneur secara keseluruhan, seperti kondisi bangunan, peralatan alaram kebakaran, dll) | F51: Berdasarkan hasil pengujian 2 unit lift ditemukan ditemukan 1 unit lift yang system ARD tidak berfungsi, interphone dan lampu emergency rusak/ mati dan tidak dilengkapi dengan petunjuk jika terjadi emergency | G51: F | H51: 2 | I51: 5 | J51: 10
A52: 2024 | B52: SH1 | C52: Ciputra Artpreneur | D52: Departemen Engineering | E52: Lain-lain (pengelolaan dan pengecekan atas keadaan atau kondisi artpreneur secara keseluruhan, seperti kondisi bangunan, peralatan alaram kebakaran, dll) | F52: Berdasarkan full opname inventory Engineering ditemukan 1 item inventory belum masuk ke dalam list inventory tool | G52: F | H52: 2 | I52: 5 | J52: 10
A53: 2024 | B53: SH1 | C53: Ciputra Artpreneur | D53: Departemen Engineering | E53: Lain-lain (pengelolaan dan pengecekan atas keadaan atau kondisi artpreneur secara keseluruhan, seperti kondisi bangunan, peralatan alaram kebakaran, dll) | F53: Berdasarkan full opname sparepart Engineering ditemukan Selisih kurang atas 2 item (20 pcs) dan selisih lebih atas 2 item (11 pcs) di mana 1 item (8 pcs) di antaranya belum masuk ke dalam list sparepart | G53: F | H53: 2 | I53: 5 | J53: 10
A54: 2024 | B54: SH1 | C54: Ciputra Artpreneur | D54: Departemen Engineering | E54: Lain-lain (pengelolaan dan pengecekan atas keadaan atau kondisi artpreneur secara keseluruhan, seperti kondisi bangunan, peralatan alaram kebakaran, dll) | F54: Berdasarkan full opname atas 54 tabung APAR ditemukan 4 tabung APAR yang sudah expired berselang 1,248 hari s/d 1,329 hari sejak tanggal expired s/d tanggal opname; 2 tabung APAR yang kondisi tekanannya habis; 5 tabung APAR yang tidak disegel/ seal terlepas; Seluruh tabung APAR tidak dilengkapi dengan kartu checklist pemeriksaan | G54: F | H54: 2 | I54: 5 | J54: 10
A55: 2024 | B55: SH1 | C55: Ciputra Artpreneur | D55: Departemen Engineering | E55: Lain-lain (pengelolaan dan pengecekan atas keadaan atau kondisi artpreneur secara keseluruhan, seperti kondisi bangunan, peralatan alaram kebakaran, dll) | F55: Berdasarkan observasi atas 70 monitor CCTV ditemukan 12 kamera CCTV rusak dan tidak diketahui waktu kerusakannya karena tidak dicatat pada logbook maupun Work Order (WO) | G55: F | H55: 2 | I55: 5 | J55: 10
A56: 2024 | B56: SH1 | C56: Ciputra Artpreneur | D56: Departemen Keuangan & Accounting | E56: Cash dan Bank Management (dilakukan opname berkala dan didukung Berita Acara, setiap mutasi yang terjadi harus dicatat dan diupdate, kas bon dicatat terpisah dari buku kas harian dan harus dimonitor batas pertanggung jawabannya) | F56: Berdasarkan sample vouching atas 60 voucher pengeluaran ditemukan 4 transaksi dengan menggunakan cheque yang keterangan “atau pembawa” nya tidak dicoret | G56: F | H56: 2 | I56: 2.5 | J56: 5
A57: 2024 | B57: SH1 | C57: Ciputra Artpreneur | D57: Departemen Keuangan & Accounting | E57: Piutang dan Collection (aging schedule dimonitor setiap bulannya dan dikirimkan surat peringatan atas konsumen yang melakukan tunggakan) | G57: NF | H57: 0 | I57: 0 | J57: 0
A58: 2024 | B58: SH1 | C58: Ciputra Artpreneur | D58: Departemen Keuangan & Accounting | E58: Internal Control Lintas Departemen (Fin Acc harus menjalankan fungsi control, bukan hanya mencatat saja) | G58: NF | H58: 0 | I58: 0 | J58: 0
A59: 2024 | B59: SH1 | C59: Ciputra Artpreneur | D59: Departemen Keuangan & Accounting | E59: Pengelolaan dan Pengamanan Asset (asset perusahaan harus dikelola dengan baik) | F59: Berdasarkan full check perhitungan penyusutan Fixed Asset per Jan’24 ditemukan selisih lebih nilai buku 1 item padahal seharusnya nilai buku sudah habis sebesar Rp 12,833; Inkonsistensi dalam melakukan penyusutan di mana penyusutan baru dilakukan setelah bulan perolehan sehingga menyebabkan selisih kurang susut sebesar Rp 4,436,826 | G59: F | H59: 2 | I59: 1 | J59: 2
A60: 2024 | B60: SH1 | C60: Ciputra Artpreneur | D60: Departemen Keuangan & Accounting | E60: Pencatatan akuntansi (penjurnalan dilakukan pada COA yang sesuai) | G60: NF | H60: 0 | I60: 0 | J60: 0
A61: 2024 | B61: SH1 | C61: Ciputra Artpreneur | D61: Departemen HRD | E61: Monitoring Lembur (setiap lembur harus didukung dengan SPL yang dibuat sebelum pekerjaan lembur dijalankan/maksimal satu hari setelah lembur, disetujui atasan yang berwenang, jam kerja yang diperhitungkan sebagai lembur adalah yang lebih kecil antara absensi vs jam di SPL, jika absensi lebih besar dan memang dibutuhkan penyesuaian jam lembur maka SPL harus direvisi ulang) | G61: NF | H61: 0 | I61: 0 | J61: 0
A62: 2024 | B62: SH1 | C62: Ciputra Artpreneur | D62: Departemen HRD | E62: Kontrak karyawan serta mutasi/pengangkatan karyawan (kontrak karyawan harus sesuai dengan ketentuan yang berlaku yaitu maksimal 2x kontrak dengan masa kontrak 3 tahun yang dimana kontrak kedua maksimum 1 tahun; mutasi/promosi harus didukung dengan IM yang disetujui yang berwenang) | F62: Berdasarkan full check pembayaran premi asuransi Mandiri Inhealth periode Jul’22 s/d Jun’23 dan periode Jul’23 s/d Jun’24 atas 15 karyawan ditemukan Premi Mandiri Inhealth atas 1 karyawan lebih rendah dari plafond golongannya | G62: F | H62: 2 | I62: 1 | J62: 2
A63: 2024 | B63: SH1 | C63: Ciputra Artpreneur | D63: Departemen HRD | E63: Absensi (setiap karyawan harus melakukan absensi setiap harinya, apabila tidak absen harus didukung dengan form ijin/cuti/tugas kantor yang disetujui atasan ybs) | F63: Berdasarkan sample check absensi karyawan periode Oct’23 s/d Dec’23 atas 8 karyawan ditemukan 1 karyawan yang tidak melakukan absensi kehadiran selama 2.5 bulan sejak tanggal join; Mesin absensi error dan belum diperbaiki/ diminta IT untuk melakukan pemeriksaan (temuan ulangan) | G63: F | H63: 2 | I63: 1.5 | J63: 3
A64: 2024 | B64: SH1 | C64: Ciputra Artpreneur | D64: Departemen HRD | E64: PO HRD (Refer to PO promosi) | G64: NF | H64: 0 | I64: 0 | J64: 0
A65: 2024 | B65: SH1 | C65: Ciputra Artpreneur | D65: Departemen HRD | E65: Efektifitas jasa outsourcing (didukung dengan MOU, kinerja outsourcing harus dipastikan sesuai dengan harapan manajemen dan tidak merugikan pihak manajemen) | G65: NF | H65: 0 | I65: 0 | J65: 0
A66: 2024 | B66: SH1 | C66: Ciputra Artpreneur | D66: Departemen HRD | E66: Biaya Pengobatan (untuk biaya pengobatan yang menjadi tanggungan manajemen harus dikontrol dengan baik agar reimburse sesuai ketentuan dan tidak ada karyawan yang over plafond) | F66: Berdasarkan full check atas 2 transaksi pemberian tanda kasih ditemukan Selisih kurang bayar sebesar Rp 500,000 atas 1 transaksi pemberian tanda kasih | G66: F | H66: 2 | I66: 2 | J66: 4
A67: 2024 | B67: SH1 | C67: Ciputra Artpreneur | D67: Departemen HRD | E67: Biaya Pengobatan (untuk biaya pengobatan yang menjadi tanggungan manajemen harus dikontrol dengan baik agar reimburse sesuai ketentuan dan tidak ada karyawan yang over plafond) | F67: Berdasarkan full check atas 8 transaksi penggantian biaya kesehatan karyawan ditemukan 1 transaksi penggantian biaya kesehatan karyawan yang tidak sesuai dengan ketentuan yang berlaku sehingga menyebabkan selisih lebih bayar ke karyawan sebesar Rp 160,000 | G67: F | H67: 2 | I67: 2 | J67: 4
A68: 2024 | B68: SH1 | C68: Ciputra Artpreneur | D68: Departemen HRD | E68: Fasilitas kantor (setiap fasilitas yang secara khusus diberikan kepada karyawan harus didukung dengan surat serah terima sehingga karyawan tersebut harus bertanggung jawab atas hal tersebut). | G68: NF | H68: 0 | I68: 0 | J68: 0
A69: 2023 | B69: SH1 | C69: Citra City Balikpapan | D69: Departemen Marketing | E69: Proses Penetapan Pricelist Baru: (PL baru harus didukung dengan analisa perhitungan harga jual dan disetujui s/d Dir Pro karena terkait unsur margin dan harus mengcover semua produk yang akan dipasarkan serta cara bayar yang ditawarkan seperti: tunai, KPR dan inhouse dimana harga KPR lebih murah dari inhouse). | G69: NF | H69: 0 | I69: 0 | J69: 0
A70: 2023 | B70: SH1 | C70: Citra City Balikpapan | D70: Departemen Marketing | E70: Transaksi Penjualan: (harga jual yang dikenakan harus sesuai dengan PL, setiap keringanan yang diberikan (diskon harga maupun kelonggaran cara bayar) harus didukung persetujuan yang berwenang sesuai koridor). | G70: NF | H70: 0 | I70: 0 | J70: 0
A71: 2023 | B71: SH1 | C71: Citra City Balikpapan | D71: Departemen Marketing | E71: Penerbitan SPT untuk transaksi baru (baik secara manual ataupun melalui software): (penerbitan SPT harus dilakukan melalui system, dicetak setelah bayar tanda jadi, diisi lengkap dan ditandatangani oleh personil yang tercantum di SPT). | F71: Berdasarkan full check atas 22 transaksi penjualan ditemukan 2 transaksi SPT belum ditandatangani oleh konsumen dan Manajemen berselang 33 hari sejak tanggal SPT s/d pull out audit 2 Nov’23 | G71: F | H71: 2 | I71: 1 | J71: 2
A72: 2023 | B72: SH1 | C72: Citra City Balikpapan | D72: Departemen Marketing | E72: Perubahan transaksi lama (perubahan transaksi harus dilakukan melalui modul perubahan transaksi lama, harus cetak SPT baru, dokumen pendukung/persyaratan yang harus dipenuhi, dikenakan biaya admin, harus ada persetujuan untuk non standar). | G72: NF | H72: 0 | I72: 0 | J72: 0
A73: 2023 | B73: SH1 | C73: Citra City Balikpapan | D73: Departemen Marketing | E73: Ganti nama (semua transaksi ganti nama harus disertai dengan dokumen pendukung dan setiap keringanan yang diberikan harus didukung dokumen dan persetujuan yang berwenang sesuai koridor dan SPT lam atetap difile). | G73: NF | H73: 0 | I73: 0 | J73: 0
A74: 2023 | B74: SH1 | C74: Citra City Balikpapan | D74: Departemen Marketing | E74: Alih hak (semua transaksi alih hak harus disertai dengan surat pernyataan pihak 1 dan 2 serta setiap keringanan yang diberikan harus didukung dokumen dan persetujuan yang berwenang sesuai koridor dan SPT lama tetap difile). | G74: NF | H74: 0 | I74: 0 | J74: 0
A75: 2023 | B75: SH1 | C75: Citra City Balikpapan | D75: Departemen Marketing | E75: Pindah blok (semua transaksi pindah blok mengikuti harga baru, setiap keringanan yang diberikan harus didukung dokumen dan persetujuan yang berwenang sesuai koridor dan SPT lama tetap difile). | G75: NF | H75: 0 | I75: 0 | J75: 0
A76: 2023 | B76: SH1 | C76: Citra City Balikpapan | D76: Departemen Marketing | E76: Ganti cara bayar (semua transaksi ganti cara bayar menggunakan harga baru dan SPT lama tetap di file) | G76: NF | H76: 0 | I76: 0 | J76: 0
A77: 2023 | B77: SH1 | C77: Citra City Balikpapan | D77: Departemen Marketing | E77: Pembatalan (ketentuan pembatalan harus sesuai dengan yang tertera pada SPT dan SPPJB a.l. nunggak 3 bulan berturut-turut, termasuk mengenai uang hangus akibat pembatalan). | G77: NF | H77: 0 | I77: 0 | J77: 0
A78: 2023 | B78: SH1 | C78: Citra City Balikpapan | D78: Departemen Marketing | E78: Sistem Komisi Penjualan dan Implementasinya (komisi dibayarkan sesuai tariff, dan memenuhi persyaratan a.l. dibayarkan setelah penandatanganan SPPJB, DP 20% lunas, dan memperhitungkan pembatalan). | G78: NF | H78: 0 | I78: 0 | J78: 0
A79: 2023 | B79: SH1 | C79: Citra City Balikpapan | D79: Departemen Marketing | E79: Kegiatan Promosi (memastikan bahwa pembelanjaan promosi sesuai dengan budget yang telah ditetapkan; dilakukan sesuai dengan prosedur pengadaan barang yaitu dengan SPK/PO, perbandingan harga minimal 3 supplier, disetujui sesuai koridor; pengelolaan atas barang yang ada dilakukan dengan baik). | F79: Berdasarkan sample check atas 31 tanda terima hadiah konsumen selama periode Nov’22 s/d Sep’23, ditemukan seluruh tanda terima hadiah konsumen tidak dilengkapi dengan copy identitas penerima di mana 3 tanda terima hadiah konsumen di antaranya nama penerima hadiah tidak sesuai dengan nama konsumen namun tidak dilengkapi dengan Surat Kuasa dan copy identitas penerima. | G79: F | H79: 2 | I79: 3 | J79: 6
A80: 2023 | B80: SH1 | C80: Citra City Balikpapan | D80: Departemen Marketing | E80: Kebijakan ubah desain (Harus didukung dengan form yang ditandatangani oleh konsumen bahwa waktu ST tidak mengikat & hilangnya garansi manajemen, pihak kontraktor harus menandatangani bahwa segala biaya ubah desain merupakan tanggung jawab kontraktor dengan konsumen sehingga apabila konsumen wanprestasi melunasi pembayaran maka bukan tanggung jawab manajemen untuk melunasi dan kontraktor harus memberikan garansi kepada konsumen mengganti garansi manajemen; perubahan desain konsumen harus sesuai dengan GSB manajemen). | G80: NF | H80: 0 | I80: 0 | J80: 0
A81: 2023 | B81: SH1 | C81: Citra City Balikpapan | D81: Departemen Legal | E81: Legalitas Konsumen (SPPJB dibuat dan ditandatangani maksimal dalam waktu 30 hari setelah SPT, klausul SPPJB mengacu pada ketentuan Kantor Pusat, dicetak dalam bentuk barang cetakan, konsumen yang sudah lunas harus segera AJB agar sertifikat tidak expired, untuk konsumen belum lunas namun bangunan sudah siap maka harus didukung dengan perjanjian pinjam pakai notariil dengan progress bayar minimum 80%). | F81: Berdasarkan full check atas 60 transaksi penjualan ditemukan 5 transaksi PPJB yang telah ditandatangani namun belum diinput di EREMS berkisar 349 hari s/d 2,517 hari sejak tanggal PPJB s/d cut off audit 30 Sep’23 | G81: F | H81: 1 | I81: 1 | J81: 1
A82: 2023 | B82: SH1 | C82: Citra City Balikpapan | D82: Departemen Legal | E82: Evaluasi tingkat pencairan dana KPR, khususnya dana retensi apakah sesuai dengan rencana schedule/estimasi awal (saat akad harus segera dilakukan pencairan tahap I, retensinya akan dicairkan sesuai dengan ketentuan yang ada namun pihak manajemen harus melakukan monitoring dana retensi tersebut untuk segera dicairkan setelah semua persyaratan dipenuhi). | F82: Berdasarkan full check atas 6 unit dengan cara bayar KPR yang belum melakukan akad kredit ditemukan 2 transaksi KPR yang sudah memenuhi syarat akad kredit (sudah lunas UM) namun belum dilakukan akad kredit berkisar 31 hari dan 136 hari sejak tanggal seharusnya akad kredit/ lunas UM/ tanggal SP3K terbit (diambil paling belakang) s/d pull out audit 2 Nov’23 | G82: F | H82: 2 | I82: 2 | J82: 4
A83: 2023 | B83: SH1 | C83: Citra City Balikpapan | D83: Departemen Legal | E83: Tidak ada masalah legalitas tanah untuk tanah yang sudah dipasarkan (monitoring legalitas pertanahan terkait Dept Marketing sehingga tidak ada kendala dalam penjualan dan tidak ada komplain dikarenakan masalah legalitas). | F83: Berdasarkan full opname atas 20 Sertifikat SHGB ditemukan 7 Sertifikat SHGB disimpan di partner, di mana 4 sertifikat di antaranya tanpa tanda terima dokumen ke pihak partner | G83: F | H83: 2 | I83: 2.5 | J83: 5
A84: 2023 | B84: SH1 | C84: Citra City Balikpapan | D84: Departemen Legal | E84: Tidak ada masalah legalitas tanah untuk tanah yang sudah dipasarkan (monitoring legalitas pertanahan terkait Dept Marketing sehingga tidak ada kendala dalam penjualan dan tidak ada komplain dikarenakan masalah legalitas). | F84: Berdasarkan full check luas tanah atas 20 Sertifikat SHGB, ditemukan 2 sertifikat SHGB yang luasannya (m2) tidak sesuai dengan yang tercantum pada SP & EREMS berkisar -10 m2 s/d 4 m2 sehingga menyebabkan konsumen lebih bayar sebesar Rp 105,000,000 dan kurang bayar sebesar Rp 42,000,000 (temuan ulangan) | G84: F | H84: 2 | I84: 2.5 | J84: 5
A85: 2023 | B85: SH1 | C85: Citra City Balikpapan | D85: Departemen QS | E85: Prosedur Tender dan Penerbitan SPK hasil Tender (setiap penerbitan SPK harus didahului dengan tender/perbandingan harga; untuk pekerjaan bangunan diijinkan repeat order dengan syarat diberikan kepada pemenang/peserta tender dengan harga yang sama; untuk prasarana tidak diijinkan repeat melainkan harus tender/minimal perbandingan harga; SPK didukung dengan persetujuan sesuai koridor yang berwenang; setiap pengecualian/SPK tunjuk langsung harus sesuai dengan koridor persetujuan tunjuk langsung). | F85: Berdasarkan sample check atas 20 SPK ditemukan 1 SPK Tunjuk Langsung yang Internal Memo Tunjuk Langsungnya dibuat berselang 3 hari setelah tanggal SPK terbit | G85: F | H85: 2 | I85: 1 | J85: 2
A86: 2023 | B86: SH1 | C86: Citra City Balikpapan | D86: Departemen QS | E86: Pembelanjaan Dept QS (dilakukan sesuai dengan prosedur pengadaan barang yaitu dengan SPK/PO, perbandingan harga minimal 3 supplier, disetujui sesuai koridor; pengelolaan atas barang yang ada dilakukan dengan baik). | F86: Berdasarkan full check atas 21 PO ditemukan 1 PO Tunjuk Langsung yang Internal Memo Tunjuk Langsungnya diterbitkan berselang 2 hari setelah tanggal PO terbit | G86: F | H86: 2 | I86: 1 | J86: 2
A87: 2023 | B87: SH1 | C87: Citra City Balikpapan | D87: Departemen QS | E87: Pekerjaan Tambah/Kurang dan Pekerjaan Mendesak (setiap pekerjaan harus didukung dengan Instruksi Lapangan/IL dan untuk mendapatkan harga satuan pekerjaan mendesak/item baru dalam pekerjaan tambah kurang akan ditindaklanjuti dengan negosiasi harga maksimum 2 minggu dari tanggal IL hingga terbit EIL (Evaluasi Instruksi Lapangan). Khusus untuk pekerjaan tambah/kurang jenis pekerjaan harus identik dengan SPK induk sehingga harga satuan mengacu ke SPK induk. Setelah pekerjaan selesai, dilakukan opname bersama untuk menentukan volume dan dituangkan dalam VO/SPK Addendum). | G87: NF | H87: 0 | I87: 0 | J87: 0
A88: 2023 | B88: SH1 | C88: Citra City Balikpapan | D88: Departemen QS | E88: Kebijakan Material Reference by Owner (Material RBO) dan konsekuensinya apakah ada potensi pelanggaran kontrol atau kelemahan lain yang menghambat pembangunan, target ST maupun kualitas bangunan (setiap barang RBO harus didukung dengan PKS sehingga harga mengikat). | G88: NF | H88: 0 | I88: 0 | J88: 0
A89: 2023 | B89: SH1 | C89: Citra City Balikpapan | D89: Departemen QS | E89: Kontraktor bermasalah, penyebabnya dan bagaimana manajemen menyelesaikan masalah yang ada (mengantisipasi kerugian yang dialami manajemen/ biaya take over pekerjaan lebih besar dari SPK awal akibat dari kontraktor yang tidak bonafid seperti: meninggalkan pekerjaan sebelum diselesaikan karena kontraktor terhambat cash flow, dll). | G89: NF | H89: 0 | I89: 0 | J89: 0
A90: 2023 | B90: SH1 | C90: Citra City Balikpapan | D90: Departemen QS | E90: Piutang kontraktor/Supplier yang timbul akibat RBO; monitoring dan penagihan/pemotongannya apakah sesuai dengan yang direncanakan/semestinya | G90: NF | H90: 0 | I90: 0 | J90: 0
A91: 2023 | B91: SH1 | C91: Citra City Balikpapan | D91: Departemen Teknik/konstruksi | E91: Progress Lapangan, Berita Acara Prestasi dan Sertifikat Pembayaran (pengawas lapangan harus melakukan monitoring atas kemajuan proyek secara rutin, memasukkan dalam rekapan progress sehingga dapat dipantau oleh lintas Dept, untuk pekerjaan bangunan setelah selesai dapat langsung dilakukan ST Konsumen apabila konsumen telah lunas sehingga masa garansi masih tanggung jawab kontraktor). | F91: Berdasarkan sample check atas 3 pekerjaan prasarana pada tanggal 31 Okt’23 ditemukan perbedaan spesifikasi material antara actual dengan Laporan Progress Kemajuan Pekerjaan yang tidak didukung dengan approval perubahan spesifikasi material yang ditandatangani s/d GM | G91: F | H91: 2 | I91: 1 | J91: 2
A92: 2023 | B92: SH1 | C92: Citra City Balikpapan | D92: Departemen Teknik/konstruksi | E92: Serah Terima Kontraktor vs Serah Terima Konsumen (sedapat mungkin, ST Konsumen harus dilakukan sebelum ST I Kontraktor sehingga masa garansi masih menjadi tanggung jawab kontraktor atau minimal dilakukan bersamaan dengan ST I Kontraktor). | G92: NF | H92: 0 | I92: 0 | J92: 0
A93: 2023 | B93: SH1 | C93: Citra City Balikpapan | D93: Departemen Teknik/konstruksi | E93: Tingkat rumah stock yang tinggi; penyebab dan penyelesaiannya termasuk komunikasi ke bagian Marketing untuk dapat aktif dipasarkan. | F93: Berdasarkan observasi lapangan atas ruko stock yang belum terjual tanggal 31 Okt’23 ditemukan adanya penyimpanan barang ex SH3B tanpa dilengkapi dengan list barang | G93: F | H93: 2 | I93: 1 | J93: 2
A94: 2023 | B94: SH1 | C94: Citra City Balikpapan | D94: Departemen Estate (City Management) | E94: Analisa aging schedule, collectability dan upaya penagihan (Tingginya tingkat tunggakan khususnya untuk rumah yang berstatus huni; Lemahnya tingkat collectability atas penerimaan). | F94: Berdasarkan full check atas 10 unit yang memiliki tunggakan IPL, ditemukan overstated tunggakan sebesar Rp 1,287,600 karena 1 unit SH/01 yang mendapatkan program free IPL namun tercatat sebagai aging; Laporan collectability yang dibuat secara manual oleh Departemen Estate tidak memperhitungkan nilai tunggakan/ aging sehingga collectability terlihat bagus | G94: F | H94: 2 | I94: 2 | J94: 4
A95: 2023 | B95: SH1 | C95: Citra City Balikpapan | D95: Departemen Estate (City Management) | E95: Penerimaan Estate setiap penerimaan harus disetorkan pada hari tersebut ke General Kasir yang didukung dengan tanda terima pada log book, kuitansi penerimaan harus prenumbered, kontrol dan prosedur dalam penagihan dan penerimaan harus dilakukan dengan baik/tidak ada penerimaan yang belum disetorkan) | G95: NF | H95: 0 | I95: 0 | J95: 0
A96: 2023 | B96: SH1 | C96: Citra City Balikpapan | D96: Departemen Estate (City Management) | E96: Penerimaan retribusi WTP, IPLK, Pasar modern, Kios, dll (Pasar modern dan Kios dapat dipisahkan apabila pos penerimaan dan flow of processnya tidak sama dengan WTP/IPLK) | F96: Berdasarkan sample check perhitungan tarif IPL periode Nov’22 s/d Sep’23 ditemukan tagihan IPL atas 3 unit sebesar Rp 3,050,000 yang belum dibayarkan oleh konsumen | G96: F | H96: 2 | I96: 1 | J96: 2
A97: 2023 | B97: SH1 | C97: Citra City Balikpapan | D97: Departemen Estate (City Management) | E97: Kavling bangun & Renovasi rumah (konsumen kavling harus membayar uang jaminan membangun saat akan melakukan pembangunan rumah/renovasi rumah apabila konsumen membeli rumah, harus ada IMB saat membangun, pembayaran IMB melalui developer tidak disalahgunakan) | G97: NF | H97: 0 | I97: 0 | J97: 0
A98: 2023 | B98: SH1 | C98: Citra City Balikpapan | D98: Departemen Estate (City Management) | E98: Efektifitas jasa outsourcing (didukung dengan MOU, kinerja outsourcing harus dipastikan sesuai dengan harapan manajemen dan tidak merugikan pihak manajemen) | F98: Berdasarkan pemeriksaan atas Perjanjian Kerjasama (PKS) terkait tenaga keamanan ditemukan Perjanjian Kerjasama (PKS) yang tidak dilengkapi klausul denda/sanksi atas kekurangan personil yang tidak hadir | G98: F | H98: 2 | I98: 1 | J98: 2
A99: 2023 | B99: SH1 | C99: Citra City Balikpapan | D99: Departemen Estate (City Management) | E99: Quality Audit & Risk Management (mengantisipasi resiko hazard risk dan good environment) | G99: NF | H99: 0 | I99: 0 | J99: 0
A100: 2023 | B100: SH1 | C100: Citra City Balikpapan | D100: Departemen Keuangan & Accounting | E100: Cash dan Bank Management (dilakukan opname berkala dan didukung Berita Acara, setiap mutasi yang terjadi harus dicatat dan diupdate, kas bon dicatat terpisah dari buku kas harian dan harus dimonitor batas pertanggung jawabannya) | F100: Berdasarkan sample check atas 343 transaksi yang pembayarannya menggunakan cheque/giro selama periode Jan’23 s/d Sep’23 ditemukan 1 transaksi pembayaran yang dilakukan dengan pemecahan/splitzing cheque dan tidak dilengkapi dengan approval splitzing | G100: F | H100: 2 | I100: 1 | J100: 2
A101: 2023 | B101: SH1 | C101: Citra City Balikpapan | D101: Departemen Keuangan & Accounting | E101: Piutang dan Collection (aging schedule dimonitor setiap bulannya dan dikirimkan surat peringatan atas konsumen yang melakukan tunggakan) | F101: Berdasarkan analisa akun Escrow Bank Maybank (No.Akun: 19.80.114) per 30 Sep’23, ditemukan saldo Escrow understated sebesar Rp 20,370,591 karena terdapat kesalahan pencatatan jurnal | G101: F | H101: 2 | I101: 1 | J101: 2
A102: 2023 | B102: SH1 | C102: Citra City Balikpapan | D102: Departemen Keuangan & Accounting | E102: Internal Control Lintas Departemen (Fin Acc harus menjalankan fungsi control, bukan hanya mencatat saja) | F102: Berdasarkan analisa Akun Uang Titipan BBN Akte (Akun: 21.50.310) per 31 Des’22 sebesar Rp 796,362,869 ditemukan uang masuk atas 2 unit/konsumen batal yang masih outstanding berkisar 1,097 hari dari tanggal pembatalan s/d tanggal 31 Des’22; 5 unit yang telah AJB namun Uang Titipan BBN Akte sebesar Rp 30,899,376 masih outstanding berkisar 1,258 hari s/d 1,786 hari (> 3 tahun) (temuan ulangan) | G102: F | H102: 2 | I102: 2.5 | J102: 5
A103: 2023 | B103: SH1 | C103: Citra City Balikpapan | D103: Departemen Keuangan & Accounting | E103: Perhitungan development cost per kawasan untuk Pembebanan Biaya (HPP) | G103: NF | H103: 0 | I103: 0 | J103: 0
...

Sheet Proyek
A1: No | B1: SH | C1: Project | D1: Total | E1: Finding | F1: Non-Finding | G1: Type | H1: Subtype | I1: Description
A2: 1 | B2: SH2 | C2: Asuransi Ciputra Life | D2: =COUNTIF(Master!C:C,Proyek!C2) -> 55 | E2: =COUNTIFS(Master!C:C,Proyek!C2,Master!G:G,"F") -> 23 | F2: =COUNTIFS(Master!C:C,Proyek!C2,Master!G:G,"NF") -> 32 | G2: Others | H2: Insurance
A3: 2 | B3: SH2 | C3: Bizpark 3 Bekasi | D3: =COUNTIF(Master!C:C,Proyek!C3) -> 32 | E3: =COUNTIFS(Master!C:C,Proyek!C3,Master!G:G,"F") -> 6 | F3: =COUNTIFS(Master!C:C,Proyek!C3,Master!G:G,"NF") -> 26 | G3: Residential | H3: Landed House
A4: 4 | B4: SH2 | C4: Bizpark Pulogadung | D4: =COUNTIF(Master!C:C,Proyek!C4) -> 67 | E4: =COUNTIFS(Master!C:C,Proyek!C4,Master!G:G,"F") -> 26 | F4: =COUNTIFS(Master!C:C,Proyek!C4,Master!G:G,"NF") -> 41 | G4: Residential | H4: Landed House
A5: 5 | B5: SH4 | C5: C Derma CWJ | D5: =COUNTIF(Master!C:C,Proyek!C5) -> 24 | E5: =COUNTIFS(Master!C:C,Proyek!C5,Master!G:G,"F") -> 11 | F5: =COUNTIFS(Master!C:C,Proyek!C5,Master!G:G,"NF") -> 13 | G5: Healthcare | H5: Clinic
A6: 6 | B6: SH1 | C6: Century21 | D6: =COUNTIF(Master!C:C,Proyek!C6) -> 40 | E6: =COUNTIFS(Master!C:C,Proyek!C6,Master!G:G,"F") -> 23 | F6: =COUNTIFS(Master!C:C,Proyek!C6,Master!G:G,"NF") -> 17 | G6: Others | H6: Broker
A7: 7 | B7: SH1 | C7: Ciputra Artpreneur | D7: =COUNTIF(Master!C:C,Proyek!C7) -> 27 | E7: =COUNTIFS(Master!C:C,Proyek!C7,Master!G:G,"F") -> 16 | F7: =COUNTIFS(Master!C:C,Proyek!C7,Master!G:G,"NF") -> 11 | G7: Others | H7: Theatre
A8: 8 | B8: SH3A | C8: Ciputra Beach Resort | D8: =COUNTIF(Master!C:C,Proyek!C8) -> 49 | E8: =COUNTIFS(Master!C:C,Proyek!C8,Master!G:G,"F") -> 27 | F8: =COUNTIFS(Master!C:C,Proyek!C8,Master!G:G,"NF") -> 22 | G8: Residential | H8: Landed House
A9: 9 | B9: SH4 | C9: Ciputra Hospital Citra Garden City | D9: =COUNTIF(Master!C:C,Proyek!C9) -> 120 | E9: =COUNTIFS(Master!C:C,Proyek!C9,Master!G:G,"F") -> 74 | F9: =COUNTIFS(Master!C:C,Proyek!C9,Master!G:G,"NF") -> 46 | G9: Healthcare | H9: Hospital
A10: 10 | B10: SH4 | C10: Ciputra Hospital Citra Raya Tangerang | D10: =COUNTIF(Master!C:C,Proyek!C10) -> 146 | E10: =COUNTIFS(Master!C:C,Proyek!C10,Master!G:G,"F") -> 83 | F10: =COUNTIFS(Master!C:C,Proyek!C10,Master!G:G,"NF") -> 63 | G10: Healthcare | H10: Hospital
A11: 11 | B11: SH3A | C11: Ciputra Hospitality (Citra Dream HO) | D11: =COUNTIF(Master!C:C,Proyek!C11) -> 17 | E11: =COUNTIFS(Master!C:C,Proyek!C11,Master!G:G,"F") -> 10 | F11: =COUNTIFS(Master!C:C,Proyek!C11,Master!G:G,"NF") -> 7 | G11: Commercial | H11: Office
A12: 12 | B12: SH3A | C12: Ciputra International Puri | D12: =COUNTIF(Master!C:C,Proyek!C12) -> 97 | E12: =COUNTIFS(Master!C:C,Proyek!C12,Master!G:G,"F") -> 52 | F12: =COUNTIFS(Master!C:C,Proyek!C12,Master!G:G,"NF") -> 45 | G12: Commercial | H12: Office, Apartment, Hotel | I12: Ciputra International Puri merupakan proyek pengembangan mixed-use dari PT Ciputra Property (anak perusahaan) yang terletak di kawasan strategis Jakarta Barat dan mudah diakses dari Bandara Internasional Soekarno-Hatta. Diluncurkan pada tahun 2014, proyek ini memiliki luas lahan sampai dengan 7,5 hektar. Ciputra International Puri akan mengembangkan 10 tower, yang terdiri dari 6 gedung perkantoran, 3 hunian bertingkat, dan 1 hotel. Perencanaan yang baik, konektivitas antar tower yang mudah, serta desain yang mewah dan modern akan semakin menambah tingkat kenyamanan dan eksklusif dari kawasan superblok ini.
A13: 13 | B13: SH4 | C13: Ciputra Medical Center (CMC) | D13: =COUNTIF(Master!C:C,Proyek!C13) -> 99 | E13: =COUNTIFS(Master!C:C,Proyek!C13,Master!G:G,"F") -> 52 | F13: =COUNTIFS(Master!C:C,Proyek!C13,Master!G:G,"NF") -> 47 | G13: Healthcare | H13: Clinic
A14: 14 | B14: SH4 | C14: Ciputra Mitra Hospital | D14: =COUNTIF(Master!C:C,Proyek!C14) -> 44 | E14: =COUNTIFS(Master!C:C,Proyek!C14,Master!G:G,"F") -> 25 | F14: =COUNTIFS(Master!C:C,Proyek!C14,Master!G:G,"NF") -> 19 | G14: Healthcare | H14: Hospital
A15: 15 | B15: SH4 | C15: Ciputra SMG Eye Clinic | D15: =COUNTIF(Master!C:C,Proyek!C15) -> 35 | E15: =COUNTIFS(Master!C:C,Proyek!C15,Master!G:G,"F") -> 15 | F15: =COUNTIFS(Master!C:C,Proyek!C15,Master!G:G,"NF") -> 20 | G15: Healthcare | H15: Clinic
A16: 16 | B16: SH2 | C16: Ciputra Surabaya Padang Golf | D16: =COUNTIF(Master!C:C,Proyek!C16) -> 132 | E16: =COUNTIFS(Master!C:C,Proyek!C16,Master!G:G,"F") -> 57 | F16: =COUNTIFS(Master!C:C,Proyek!C16,Master!G:G,"NF") -> 75 | G16: Commercial | H16: Golf Course, Family Club, Wedding | I16: Ciputra Golf & Family Club Surabaya is the biggest and the most complete golf course in East Java, designed by Andy Dye from Dye Design Corp., a reputable golf course designer in the world. The designer took advantage of the range of elevation in developing the course. Following the natural hill and valley topography of the area, the course is designed stadium style with the holes in the valley.
A17: 17 | B17: SH2 | C17: Ciputra The Taman Dayu | D17: =COUNTIF(Master!C:C,Proyek!C17) -> 131 | E17: =COUNTIFS(Master!C:C,Proyek!C17,Master!G:G,"F") -> 38 | F17: =COUNTIFS(Master!C:C,Proyek!C17,Master!G:G,"NF") -> 93 | G17: Residential | H17: Landed House
A18: 18 | B18: SH3A | C18: Ciputra World Jakarta 1 | D18: =COUNTIF(Master!C:C,Proyek!C18) -> 38 | E18: =COUNTIFS(Master!C:C,Proyek!C18,Master!G:G,"F") -> 28 | F18: =COUNTIFS(Master!C:C,Proyek!C18,Master!G:G,"NF") -> 10 | G18: Commercial | H18: Mall, Office
A19: 19 | B19: SH3A | C19: Ciputra World Jakarta 2 | D19: =COUNTIF(Master!C:C,Proyek!C19) -> 44 | E19: =COUNTIFS(Master!C:C,Proyek!C19,Master!G:G,"F") -> 20 | F19: =COUNTIFS(Master!C:C,Proyek!C19,Master!G:G,"NF") -> 24 | G19: Commercial | H19: Mall, Office
A20: 20 | B20: SH2 | C20: Ciputra World Surabaya Apartment | D20: =COUNTIF(Master!C:C,Proyek!C20) -> 91 | E20: =COUNTIFS(Master!C:C,Proyek!C20,Master!G:G,"F") -> 48 | F20: =COUNTIFS(Master!C:C,Proyek!C20,Master!G:G,"NF") -> 43 | G20: Commercial | H20: Apartment
A21: 21 | B21: SH2 | C21: Ciputra World Surabaya Hotel | D21: =COUNTIF(Master!C:C,Proyek!C21) -> 101 | E21: =COUNTIFS(Master!C:C,Proyek!C21,Master!G:G,"F") -> 50 | F21: =COUNTIFS(Master!C:C,Proyek!C21,Master!G:G,"NF") -> 51 | G21: Commercial | H21: Hotel
A22: 22 | B22: SH2 | C22: Ciputra World Surabaya Mall | D22: =COUNTIF(Master!C:C,Proyek!C22) -> 86 | E22: =COUNTIFS(Master!C:C,Proyek!C22,Master!G:G,"F") -> 52 | F22: =COUNTIFS(Master!C:C,Proyek!C22,Master!G:G,"NF") -> 34 | G22: Commercial | H22: Mall
A23: 23 | B23: SH3A | C23: Citra Beach Resort | D23: =COUNTIF(Master!C:C,Proyek!C23) -> 46 | E23: =COUNTIFS(Master!C:C,Proyek!C23,Master!G:G,"F") -> 22 | F23: =COUNTIFS(Master!C:C,Proyek!C23,Master!G:G,"NF") -> 24 | G23: Residential | H23: Landed House | I23: Ciputra Beach Resort terletak di Kabupaten Tabanan, Bali, membentang di atas tanah seluas 80 hektar dan garis pantai sepanjang 1,7 km. Dilengkapi oleh pemandangan laut yang mengagumkan serta pegunungan dan teras sawah, ombak berselancar yang terkenal, serta ciri khas sejarah dan kultur yang kental, Kabupaten Tabanan menawarkan pengalaman yang tak terlupakan yang hanya didapatkan di pulau Bali. Hanya 45 menit dari bandara, Ciputra Beach Resort akan menawarkan pengalaman khusus dari pulau Bali melalui resor dan hunian mewah. Ciputra Beach Resort terdiri dari beberapa cluster seperti Sadana, Nivata, dan akan mengembangkan dua tahap dan menghadirkan dua operator kelas dunia yaitu The Ritz-Carlton dan Rosewood Hotels & Resorts.
A24: 24 | B24: SH1 | C24: Citra City Balikpapan | D24: =COUNTIF(Master!C:C,Proyek!C24) -> 44 | E24: =COUNTIFS(Master!C:C,Proyek!C24,Master!G:G,"F") -> 19 | F24: =COUNTIFS(Master!C:C,Proyek!C24,Master!G:G,"NF") -> 25 | G24: Residential | H24: Landed House | I24: Citra City Balikpapan dikembangkan di atas masterplan premium seluas 9 hektar, dengan visi untuk menjadi city lifestyle center yang mendukung gaya hidup modern. Hadir dengan konsep one stop living, kawasan ini memungkinkan penghuninya merasakan kenyamanan hunian, kemudahan akses ke berbagai fasilitas, dan dukungan penuh bagi kebutuhan hidup sehari-hari dalam satu area yang terintegrasi. Kawasan ini memadukan area residensial premium dengan area komersial, menjadikannya pilihan menarik bagi mereka yang mencari perumahan di Balikpapan yang memiliki potensi nilai investasi yang terus berkembang. Baik untuk tempat tinggal maupun investasi, Citra City Balikpapan menawarkan suasana lingkungan yang menyatukan kualitas hidup dan peluang ekonomi di gerbang menuju Ibu Kota Nusantara (IKN). Masterplan Citra City Balikpapan mengusung semangat “masterpiece of prime living in the city,” menawarkan lingkungan hunian yang tak hanya fungsional, tetapi juga penuh nilai estetika dan kenyamanan. Setiap detail kawasan ini didesain untuk menciptakan standar hidup yang tinggi dan memenuhi kebutuhan masyarakat urban di Balikpapan. Dirancang dengan green concept, kawasan ini menghadirkan lingkungan bisnis dan hiburan yang eco-friendly atau ramah lingkungan. Kehadiran ruang hijau dan taman tematik tidak hanya menciptakan udara segar tetapi juga memberikan kesempatan bagi penghuni untuk menjalani gaya hidup yang lebih sehat dan berkualitas. Semua ini dipersembahkan agar Anda mendapatkan gaya hidup yang lebih baik, sejalan dengan konsep sustainable development yang menjadi prinsip dasar Ciputra Group dalam mengembangkan Citra City Balikpapan.
A25: 25 | B25: SH1 | C25: Citra City Sentul | D25: =COUNTIF(Master!C:C,Proyek!C25) -> 37 | E25: =COUNTIFS(Master!C:C,Proyek!C25,Master!G:G,"F") -> 19 | F25: =COUNTIFS(Master!C:C,Proyek!C25,Master!G:G,"NF") -> 18 | G25: Residential | H25: Landed House
A26: 26 | B26: SH3A | C26: Hotel Citra Dream Bintaro | D26: =COUNTIF(Master!C:C,Proyek!C26) -> 93 | E26: =COUNTIFS(Master!C:C,Proyek!C26,Master!G:G,"F") -> 47 | F26: =COUNTIFS(Master!C:C,Proyek!C26,Master!G:G,"NF") -> 46 | G26: Commercial | H26: Hotel
A27: 27 | B27: SH3A | C27: Hotel Citra Dream Yogyakarta | D27: =COUNTIF(Master!C:C,Proyek!C27) -> 97 | E27: =COUNTIFS(Master!C:C,Proyek!C27,Master!G:G,"F") -> 62 | F27: =COUNTIFS(Master!C:C,Proyek!C27,Master!G:G,"NF") -> 35 | G27: Commercial | H27: Hotel
A28: 28 | B28: SH1 | C28: Citra Garden Bintaro | D28: =COUNTIF(Master!C:C,Proyek!C28) -> 37 | E28: =COUNTIFS(Master!C:C,Proyek!C28,Master!G:G,"F") -> 26 | F28: =COUNTIFS(Master!C:C,Proyek!C28,Master!G:G,"NF") -> 11 | G28: Residential | H28: Landed House
A29: 29 | B29: SH1 | C29: Citra Garden BMW Cilegon | D29: =COUNTIF(Master!C:C,Proyek!C29) -> 131 | E29: =COUNTIFS(Master!C:C,Proyek!C29,Master!G:G,"F") -> 53 | F29: =COUNTIFS(Master!C:C,Proyek!C29,Master!G:G,"NF") -> 78 | G29: Residential | H29: Landed House
A30: 30 | B30: SH1 | C30: Citra Garden Malang | D30: =COUNTIF(Master!C:C,Proyek!C30) -> 45 | E30: =COUNTIFS(Master!C:C,Proyek!C30,Master!G:G,"F") -> 16 | F30: =COUNTIFS(Master!C:C,Proyek!C30,Master!G:G,"NF") -> 29 | G30: Residential | H30: Landed House
A31: 31 | B31: SH1 | C31: Citra Garden Puri Jakarta | D31: =COUNTIF(Master!C:C,Proyek!C31) -> 58 | E31: =COUNTIFS(Master!C:C,Proyek!C31,Master!G:G,"F") -> 31 | F31: =COUNTIFS(Master!C:C,Proyek!C31,Master!G:G,"NF") -> 27 | G31: Residential | H31: Landed House
A32: 32 | B32: SH1 | C32: Citra Garden Serpong | D32: =COUNTIF(Master!C:C,Proyek!C32) -> 41 | E32: =COUNTIFS(Master!C:C,Proyek!C32,Master!G:G,"F") -> 26 | F32: =COUNTIFS(Master!C:C,Proyek!C32,Master!G:G,"NF") -> 15 | G32: Residential | H32: Landed House
A33: 33 | B33: SH2 | C33: Citra Garden Sidoarjo | D33: =COUNTIF(Master!C:C,Proyek!C33) -> 146 | E33: =COUNTIFS(Master!C:C,Proyek!C33,Master!G:G,"F") -> 55 | F33: =COUNTIFS(Master!C:C,Proyek!C33,Master!G:G,"NF") -> 91 | G33: Residential | H33: Landed House
A34: 34 | B34: SH2 | C34: Citra Grand CBD Cibubur | D34: =COUNTIF(Master!C:C,Proyek!C34) -> 48 | E34: =COUNTIFS(Master!C:C,Proyek!C34,Master!G:G,"F") -> 12 | F34: =COUNTIFS(Master!C:C,Proyek!C34,Master!G:G,"NF") -> 36 | G34: Residential | H34: Landed House
A35: 35 | B35: SH2 | C35: Citra Grand Semarang | D35: =COUNTIF(Master!C:C,Proyek!C35) -> 202 | E35: =COUNTIFS(Master!C:C,Proyek!C35,Master!G:G,"F") -> 78 | F35: =COUNTIFS(Master!C:C,Proyek!C35,Master!G:G,"NF") -> 124 | G35: Residential | H35: Landed House
A36: 36 | B36: SH2 | C36: Citra Harmoni Sidoarjo | D36: =COUNTIF(Master!C:C,Proyek!C36) -> 141 | E36: =COUNTIFS(Master!C:C,Proyek!C36,Master!G:G,"F") -> 57 | F36: =COUNTIFS(Master!C:C,Proyek!C36,Master!G:G,"NF") -> 84 | G36: Residential | H36: Landed House
... A112: 112 | B112: SH3B | C112: Vidaview Apartment | D112: =COUNTIF(Master!C:C,Proyek!C112) -> 45 | E112: =COUNTIFS(Master!C:C,Proyek!C112,Master!G:G,"F") -> 20 | F112: =COUNTIFS(Master!C:C,Proyek!C112,Master!G:G,"NF") -> 25 | G112: Commercial | H112: Apartment
